dataflows_aws/VERSION
dataflows_aws/__init__.py
dataflows_aws/config.py
dataflows_aws/processors/__init__.py
dataflows_aws/processors/change_acl_on_s3.py
dataflows_aws/processors/dump_to_s3.py
dataflows_aws-0.2.4.dist-info/LICENSE.md
dataflows_aws-0.2.4.dist-info/METADATA
dataflows_aws-0.2.4.dist-info/WHEEL
dataflows_aws-0.2.4.dist-info/top_level.txt
dataflows_aws-0.2.4.dist-info/RECORD
