Metadata-Version: 2.1
Name: dataflows-aws
Version: 0.2.4
Summary: A utility library for working with Table Schema in Python
Home-page: https://github.com/frictionlessdata/dataflows-aws
Author: Open Knowledge Foundation
Author-email: info@okfn.org
License: MIT
Keywords: frictionless data,open data,json schema,table schema,data package,tabular data package
Classifier: Development Status :: 4 - Beta
Classifier: Environment :: Web Environment
Classifier: Intended Audience :: Developers
Classifier: License :: OSI Approved :: MIT License
Classifier: Operating System :: OS Independent
Classifier: Programming Language :: Python :: 3.7
Classifier: Topic :: Internet :: WWW/HTTP :: Dynamic Content
Classifier: Topic :: Software Development :: Libraries :: Python Modules
License-File: LICENSE.md
Requires-Dist: six
Requires-Dist: boto3
Requires-Dist: dataflows
Provides-Extra: develop
Requires-Dist: moto[server] ; extra == 'develop'
Requires-Dist: pytest-cov ; extra == 'develop'
Requires-Dist: pytest ; extra == 'develop'
Requires-Dist: pylama ; extra == 'develop'
Requires-Dist: mock ; extra == 'develop'
Requires-Dist: tox ; extra == 'develop'
